{
  "$schema": "https://schemas.wp.org/trunk/block.json",
  "apiVersion": 2,
  "name": "running-blog/graph",
  "title": "Graph",
  "category": "widgets",
  "description": "Adds a graph",
  "keywords": [
    "search"
  ],
  "version": "1",
  "textdomain": "running-blog",
  "editorScript": "file:./index.js",
  "attributes": {
    "graphType": {
      "type": "string",
      "default": "Select"
    },
    "dataType": {
      "type": "string",
      "default": "Select"
    },
    "span": {
      "type": "number",
      "default": 6
    }
  },
  "style": "file:./index.css"
}